[
  {
    "email": "Shakira.Weissnat17@yahoo.com",
    "password": "Bf28d7xeWRFQHj3",
    "createdAt": "2021-05-29T13:26:23.354Z",
    "updatedAt": "2021-05-29T13:26:23.354Z"
  },
  {
    "email": "Maiya_Von@yahoo.com",
    "password": "UpXHXU2uxtDNAB4",
    "createdAt": "2021-05-29T13:26:23.355Z",
    "updatedAt": "2021-05-29T13:26:23.355Z"
  },
  {
    "email": "Jayson.Wisozk@gmail.com",
    "password": "1COgrhFUxND16Q3",
    "createdAt": "2021-05-29T13:26:23.355Z",
    "updatedAt": "2021-05-29T13:26:23.355Z"
  },
  {
    "email": "Bria_OConnell36@gmail.com",
    "password": "mkcooqGy9I7z7K4",
    "createdAt": "2021-05-29T13:26:23.355Z",
    "updatedAt": "2021-05-29T13:26:23.355Z"
  },
  {
    "email": "Brent_Schinner55@gmail.com",
    "password": "_pRrogPWUg_M47s",
    "createdAt": "2021-05-29T13:26:23.355Z",
    "updatedAt": "2021-05-29T13:26:23.355Z"
  },
  {
    "email": "Tamia_Pollich@yahoo.com",
    "password": "U6nFR6ZJQ4gAV4z",
    "createdAt": "2021-05-29T13:26:23.355Z",
    "updatedAt": "2021-05-29T13:26:23.355Z"
  },
  {
    "email": "Graciela_McDermott@hotmail.com",
    "password": "nY6HHYERmsHgwtY",
    "createdAt": "2021-05-29T13:26:23.355Z",
    "updatedAt": "2021-05-29T13:26:23.355Z"
  },
  {
    "email": "Meta61@yahoo.com",
    "password": "DXY0AUv0vUF3nem",
    "createdAt": "2021-05-29T13:26:23.355Z",
    "updatedAt": "2021-05-29T13:26:23.355Z"
  },
  {
    "email": "Columbus17@gmail.com",
    "password": "7RYRgl1fMcgHXa6",
    "createdAt": "2021-05-29T13:26:23.355Z",
    "updatedAt": "2021-05-29T13:26:23.355Z"
  },
  {
    "email": "Kayla73@hotmail.com",
    "password": "NVG9ZAePMMa_2aa",
    "createdAt": "2021-05-29T13:26:23.356Z",
    "updatedAt": "2021-05-29T13:26:23.356Z"
  }
]